azure/monitor/opentelemetry/exporter/__init__.py
azure/monitor/opentelemetry/exporter/_connection_string_parser.py
azure/monitor/opentelemetry/exporter/_constants.py
azure/monitor/opentelemetry/exporter/_storage.py
azure/monitor/opentelemetry/exporter/_utils.py
azure/monitor/opentelemetry/exporter/_version.py
azure/monitor/opentelemetry/exporter/py.typed
azure/monitor/opentelemetry/exporter/_configuration/__init__.py
azure/monitor/opentelemetry/exporter/_configuration/_state.py
azure/monitor/opentelemetry/exporter/_configuration/_utils.py
azure/monitor/opentelemetry/exporter/_configuration/_worker.py
azure/monitor/opentelemetry/exporter/_generated/__init__.py
azure/monitor/opentelemetry/exporter/_generated/_azure_monitor_client.py
azure/monitor/opentelemetry/exporter/_generated/_configuration.py
azure/monitor/opentelemetry/exporter/_generated/_patch.py
azure/monitor/opentelemetry/exporter/_generated/_vendor.py
azure/monitor/opentelemetry/exporter/_generated/py.typed
azure/monitor/opentelemetry/exporter/_generated/aio/__init__.py
azure/monitor/opentelemetry/exporter/_generated/aio/_azure_monitor_client.py
azure/monitor/opentelemetry/exporter/_generated/aio/_configuration.py
azure/monitor/opentelemetry/exporter/_generated/aio/_patch.py
azure/monitor/opentelemetry/exporter/_generated/aio/operations/__init__.py
azure/monitor/opentelemetry/exporter/_generated/aio/operations/_azure_monitor_client_operations.py
azure/monitor/opentelemetry/exporter/_generated/models/__init__.py
azure/monitor/opentelemetry/exporter/_generated/models/_azure_monitor_client_enums.py
azure/monitor/opentelemetry/exporter/_generated/models/_models.py
azure/monitor/opentelemetry/exporter/_generated/models/_models_py3.py
azure/monitor/opentelemetry/exporter/_generated/operations/__init__.py
azure/monitor/opentelemetry/exporter/_generated/operations/_azure_monitor_client_operations.py
azure/monitor/opentelemetry/exporter/_performance_counters/__init__.py
azure_monitor_opentelemetry_exporter-1.0.0b43.dist-info/licenses/LICENSE
azure_monitor_opentelemetry_exporter-1.0.0b43.dist-info/METADATA
azure_monitor_opentelemetry_exporter-1.0.0b43.dist-info/WHEEL
azure_monitor_opentelemetry_exporter-1.0.0b43.dist-info/entry_points.txt
azure_monitor_opentelemetry_exporter-1.0.0b43.dist-info/top_level.txt
azure_monitor_opentelemetry_exporter-1.0.0b43.dist-info/RECORD
