Metadata-Version: 2.4
Name: azure-monitor-opentelemetry-exporter
Version: 1.0.0b43
Summary: Microsoft Azure Monitor Opentelemetry Exporter Client Library for Python
Home-page: https://github.com/Azure/azure-sdk-for-python/tree/main/sdk/monitor/azure-monitor-opentelemetry-exporter
Author: Microsoft Corporation
Author-email: ascl@microsoft.com
License: MIT License
Keywords: azure,azure sdk
Classifier: Development Status :: 4 - Beta
Classifier: Programming Language :: Python
Classifier: Programming Language :: Python :: 3
Classifier: Programming Language :: Python :: 3.9
Classifier: Programming Language :: Python :: 3.10
Classifier: Programming Language :: Python :: 3.11
Classifier: Programming Language :: Python :: 3.12
Classifier: License :: OSI Approved :: MIT License
Requires-Python: >=3.8
License-File: LICENSE
Requires-Dist: azure-core<2.0.0,>=1.28.0
Requires-Dist: azure-identity~=1.17
Requires-Dist: fixedint==0.1.6
Requires-Dist: msrest>=0.6.10
Requires-Dist: opentelemetry-api~=1.35
Requires-Dist: opentelemetry-sdk~=1.35
Requires-Dist: psutil<8,>=5.9
Dynamic: author
Dynamic: author-email
Dynamic: classifier
Dynamic: description
Dynamic: description-content-type
Dynamic: home-page
Dynamic: keywords
Dynamic: license
Dynamic: license-file
Dynamic: requires-dist
Dynamic: requires-python
Dynamic: summary
